{
  "$schema": "https://soustack.spec/soustack.schema.json",
  "profile": "lite",
  "name": "3 large eggplants peeled",
  "stacks": {},
  "ingredients": [],
  "instructions": [
    "Salt",
    "Egg wash",
    "Italian seasoning",
    "Breadcrumbs",
    "Vegetable oil",
    "Parmesan cheese",
    "Mozzarella cheese",
    "Tomato sauce",
    "Stack eggplant with salt in between every other to drain out bitterness for ½ hour",
    "Rinse it with cool water, pat dry",
    "Dip in egg wash and then in breadcrumbs with Italian seasoning",
    "Fry till crispy in vegetable oil",
    "Place a small amount of sauce in 9 x 13 pan",
    "Layer eggplant, parmesan cheese, little sauce, repeat and repeat",
    "Bake covered 35-40 minutes then add mozzarella",
    "Back in oven for 10 minutes",
    "325 degree oven"
  ],
  "metadata": {
    "ingest": {
      "pipelineVersion": "0.1.0",
      "sourcePath": "bowman.txt",
      "sourceLines": {
        "start": 1498,
        "end": 1526
      },
      "warnings": [
        "3 large eggplants peeled: Missing ingredients"
      ]
    }
  }
}