{
  "$schema": "https://soustack.spec/soustack.schema.json",
  "profile": "lite",
  "name": "RITA BOWMAN’S CHICKEN STEW/POT PIE",
  "stacks": {},
  "ingredients": [
    "3 ½ lb. chicken cut in quarters",
    "1 large chopped onion",
    "6 carrots",
    "3 celery stalks sliced",
    "2 leeks (white only) sliced",
    "Sprig of fresh thyme",
    "3 stems fresh parsley",
    "1 bay leaf",
    "2 ¼ cup chicken broth",
    "4 tbsp. butter",
    "1/2 cup flour",
    "1 ½ cup whole milk",
    "1 package cooked (well drained) frozen peas",
    "Salt & pepper"
  ],
  "instructions": [
    "By:",
    "Rita Bowman",
    "Sauté the chicken lightly in a little oil with onion",
    "Add broth and simmer 1 hour",
    "Add carrots, celery, leeks, thyme, parsley, and bay leaf",
    "Simmer to cook vegetables",
    "Remove meat from bones.",
    "Melt butter",
    "Add flour and whole milk",
    "Thicken and add to the above",
    "Season with salt & pepper",
    "Can be served with biscuits or topped with pastry and baked."
  ],
  "metadata": {
    "ingest": {
      "pipelineVersion": "0.1.0",
      "sourcePath": "bowman.txt",
      "sourceLines": {
        "start": 1625,
        "end": 1667
      }
    }
  }
}