{
  "$schema": "https://soustack.spec/soustack.schema.json",
  "profile": "lite",
  "name": "SISTER’S (SALLY – OUR FAVORITE SISTER) FISH",
  "stacks": {},
  "ingredients": [
    "Filet of sole (very thin - 2 pieces per person)",
    "2 eggs",
    "Breadcrumbs",
    "Tomatoes",
    "Onion",
    "Green pepper",
    "Parmesan cheese",
    "Salt and pepper"
  ],
  "instructions": [
    "By:",
    "Sally Bowman",
    "Wash fish with water dry with paper towel",
    "In a bowl, beat eggs, pour some bread crumbs on a plate.",
    "Dip fish in egg mixture, then into bread crumbs",
    "Spray cookie sheet with Pam and place fish on it",
    "Place fish in single layer on sheet",
    "Slice tomatoes, onion, green pepper thin and place on top of fish. Add parmesan cheese, salt, and pepper",
    "Bake 10-12 minutes in 350 degree oven.",
    "You can substitute cookie pan for heavy duty foil and cook on gas grill."
  ],
  "metadata": {
    "ingest": {
      "pipelineVersion": "0.1.0",
      "sourcePath": "bowman.txt",
      "sourceLines": {
        "start": 847,
        "end": 879
      }
    }
  }
}