{
  "$schema": "https://soustack.spec/soustack.schema.json",
  "profile": "lite",
  "name": "TERRY BOWMAN’S TEXAS CAVIAR",
  "stacks": {},
  "ingredients": [
    "1 can white corn",
    "1 can black eyed peas",
    "1 can black beans",
    "1 jar chopped Pimento",
    "1 cup chopped celery",
    "1 small to medium red onion chopped",
    "1 Small Jar Jalapeno Peppers chopped (use more or less – depends on how hot you like it)",
    "1 cup sugar",
    "1 cup apple cider vinegar",
    "1 cup canola oil"
  ],
  "instructions": [
    "By: Terry Bowman",
    "Heat oil, vinegar and sugar until sugar is dissolved",
    "Pour over all other ingredients and stir",
    "Put in refrigerator and let marinade until cool",
    "Drain before serving",
    "Serve with scoopable Fritos"
  ],
  "metadata": {
    "ingest": {
      "pipelineVersion": "0.1.0",
      "sourcePath": "bowman.txt",
      "sourceLines": {
        "start": 146,
        "end": 173
      }
    }
  }
}